{
  "version": "5",
  "dialect": "pg",
  "entries": [
    {
      "idx": 0,
      "version": "5",
      "when": 1711101297114,
      "tag": "0000_wonderful_hiroim",
      "breakpoints": true
    },
    {
      "idx": 1,
      "version": "5",
      "when": 1711621107321,
      "tag": "0001_dry_jamie_braddock",
      "breakpoints": true
    },
    {
      "idx": 2,
      "version": "5",
      "when": 1711649710886,
      "tag": "0002_striped_talon",
      "breakpoints": true
    },
    {
      "idx": 3,
      "version": "5",
      "when": 1712305132561,
      "tag": "0003_exotic_nova",
      "breakpoints": true
    }
  ]
}